lastlogtocsv/__init__.py
lastlogtocsv/__main__.py
lastlogtocsv-3.0.0.dist-info/LICENSE
lastlogtocsv-3.0.0.dist-info/METADATA
lastlogtocsv-3.0.0.dist-info/WHEEL
lastlogtocsv-3.0.0.dist-info/top_level.txt
lastlogtocsv-3.0.0.dist-info/RECORD
